BasicAlgorithmsPyLib/__init__.py
BasicAlgorithmsPyLib/math/__init__.py
BasicAlgorithmsPyLib/math/factorial.py
BasicAlgorithmsPyLib/math/fibonacci.py
BasicAlgorithmsPyLib/search/__init__.py
BasicAlgorithmsPyLib/search/binary_search.py
BasicAlgorithmsPyLib/search/linear_search.py
BasicAlgorithmsPyLib/sorting/__init__.py
BasicAlgorithmsPyLib/sorting/bubble_sort.py
BasicAlgorithmsPyLib/sorting/quick_sort.py
BasicAlgorithmsPyLib/utils/__init__.py
BasicAlgorithmsPyLib/utils/min_max.py
BasicAlgorithmsPyLib-0.0.1.dist-info/LICENSE
BasicAlgorithmsPyLib-0.0.1.dist-info/METADATA
BasicAlgorithmsPyLib-0.0.1.dist-info/WHEEL
BasicAlgorithmsPyLib-0.0.1.dist-info/top_level.txt
BasicAlgorithmsPyLib-0.0.1.dist-info/RECORD
